{
  "products": [
    {
      "id": 1,
      "product_name": "เสื้อ Oversize สีขาว",
      "category": "Oversize",
      "color": "ขาว",
      "gender": "หญิง",
      "price": 350,
      "image": "https://img.th.my-best.com/product_images/c306c877b9128d7a303eee798f47d7d8.png?ixlib=rails-4.3.1&q=70&lossless=0&w=800&h=800&fit=clip&s=c561fc32aef4507cab372bd07cbc8b7a",
      "description": "เสื้อ Oversize ผ้าฝ้ายแท้ นุ่มใส่สบาย"
    },
    {
      "id": 2,
      "product_name": "เสื้อ Oversize สีดำ",
      "category": "Oversize",
      "color": "ดำ",
      "gender": "หญิง",
      "price": 370,
      "image": "https://png.pngtree.com/png-vector/20240420/ourmid/pngtree-black-oversized-fit-t-shirt-mockup-png-image_12302566.png",
      "description": "เสื้อ Oversize สีดำทรงหลวม ใส่ชิลได้ทุกวัน"
    },
    {
      "id": 3,
      "product_name": "เสื้อ Oversize ลายกราฟิก",
      "category": "Oversize",
      "color": "ลายกราฟิก",
      "gender": "หญิง",
      "price": 390,
      "image": "https://png.pngtree.com/png-vector/20240724/ourmid/pngtree-wild-and-spirit-sporty-graphic-print-t-shirt-png-image_13049884.png",
      "description": "เสื้อ Oversize ลายกราฟิกเกาหลีสุดน่ารัก"
    },
    {
      "id": 4,
      "product_name": "เสื้อ Oversize สีครีม",
      "category": "Oversize",
      "color": "ครีม",
      "gender": "หญิง",
      "price": 360,
      "image": "https://png.pngtree.com/png-vector/20240123/ourmid/pngtree-beige-t-shirt-mockup-png-image_11464714.png",
      "description": "เสื้อ Oversize สีครีมเรียบง่าย ใส่ได้ทุกวัน"
    },
    {
      "id": 5,
      "product_name": "เสื้อ Oversize ลายดอกไม้",
      "category": "Oversize",
      "color": "ลายดอกไม้",
      "gender": "หญิง",
      "price": 380,
      "image": "https://png.pngtree.com/png-vector/20241205/ourmid/pngtree-white-t-shirt-with-floral-design-png-image_14639004.png",
      "description": "เสื้อ Oversize ลายดอกไม้ ผ้าเบา ใส่สบาย"
    },

    {
      "id": 6,
      "product_name": "เสื้อ Oversize ผู้ชาย สีเทา",
      "category": "Oversize",
      "color": "เทา",
      "gender": "ชาย",
      "price": 390,
      "image": "https://png.pngtree.com/png-clipart/20230930/original/pngtree-gray-t-shirt-mockup-realistic-t-shirt-png-image_13020286.png",
      "description": "เสื้อ Oversize ผู้ชาย สีเทาเข้ม ดูดีมีสไตล์"
    },
    {
      "id": 7,
      "product_name": "เสื้อ Oversize ผู้ชาย สีกรม",
      "category": "Oversize",
      "color": "กรม",
      "gender": "ชาย",
      "price": 400,
      "image": "https://png.pngtree.com/png-vector/20240426/ourmid/pngtree-navy-t-shirt-png-image_12322364.png",
      "description": "เสื้อ Oversize ผู้ชาย ใส่สบาย เหมาะกับทุกโอกาส"
    },
    {
      "id": 8,
      "product_name": "เสื้อ Oversize ผู้ชาย ลายกราฟิก",
      "category": "Oversize",
      "color": "ลายกราฟิก",
      "gender": "ชาย",
      "price": 410,
      "image": "https://png.pngtree.com/png-vector/20250110/ourmid/pngtree-amazon-political-t-shirt-png-image_14442621.png",
      "description": "เสื้อ Oversize ลายกราฟิกเท่ๆ สำหรับหนุ่มสตรีท"
    },
    {
      "id": 9,
      "product_name": "เสื้อ Oversize ผู้ชาย สีเขียวเข้ม",
      "category": "Oversize",
      "color": "เขียวเข้ม",
      "gender": "ชาย",
      "price": 390,
      "image": "https://png.pngtree.com/png-vector/20250729/ourmid/pngtree-olive-green-t-shirt-mockup-with-simple-textured-fabric-png-image_16917261.webp",
      "description": "เสื้อ Oversize สีเขียวเข้ม ใส่เท่ๆ ได้ทุกโอกาส"
    },

    {
      "id": 10,
      "product_name": "เสื้อ Polo ผู้ชาย สีกรม",
      "category": "Polo",
      "color": "กรม",
      "gender": "ชาย",
      "price": 450,
      "image": "https://png.pngtree.com/png-vector/20240624/ourmid/pngtree-blank-blue-polo-shirt-front-view-png-image_12844704.png",
      "description": "เสื้อโปโลชาย ทรงเรียบหรู ใส่ทำงานได้"
    },
    {
      "id": 11,
      "product_name": "เสื้อ Polo ผู้ชาย สีขาว",
      "category": "Polo",
      "color": "ขาว",
      "gender": "ชาย",
      "price": 440,
      "image": "https://png.pngtree.com/png-clipart/20250117/original/pngtree-mockup-of-male-white-polo-shirt-design-png-image_19285292.png",
      "description": "เสื้อโปโลชาย สีขาวเรียบ ใส่ได้ทุกโอกาส"
    },
    {
      "id": 12,
      "product_name": "เสื้อ Polo ผู้ชาย ลายทาง",
      "category": "Polo",
      "gender": "ชาย",
      "price": 460,
      "image": "https://png.pngtree.com/png-vector/20250902/ourmid/pngtree-men-s-blue-and-white-striped-polo-shirt-with-emblem-clipart-png-image_17353987.webp",
      "description": "เสื้อโปโลชายลายทาง เพิ่มลุคสปอร์ต"
    },
    {
      "id": 13,
      "product_name": "เสื้อ Polo ผู้หญิง สีชมพู",
      "category": "Polo",
      "color": "ชมพู",
      "gender": "หญิง",
      "price": 430,
      "image": "https://www.egosportthailand.com/wp-content/uploads/2023/02/%E0%B8%8A%E0%B8%A1%E0%B8%9E%E0%B8%B9%E0%B8%9B%E0%B8%B0%E0%B8%81%E0%B8%B2%E0%B8%A3%E0%B8%B1%E0%B8%87_optimized.png",
      "description": "เสื้อโปโลผู้หญิง สีชมพูอ่อน ใส่ทำงานหรือเที่ยวได้"
    },
    {
      "id": 14,
      "product_name": "เสื้อ Polo ผู้หญิง สีฟ้า",
      "category": "Polo",
      "color": "ฟ้า",
      "gender": "หญิง",
      "price": 440,
      "image": "https://png.pngtree.com/png-vector/20240624/ourmid/pngtree-blank-blue-polo-shirt-front-view-png-image_12844704.png",
      "description": "เสื้อโปโลผู้หญิง สีฟ้าเรียบหรู"
    },

    {
      "id": 15,
      "product_name": "เสื้อ Sweater สีเทา",
      "category": "Sweater",
      "color": "เทา",
      "gender": "ชาย",
      "price": 520,
      "image": "https://png.pngtree.com/png-vector/20240202/ourmid/pngtree-gray-sweater-mockup-cutout-png-file-png-image_11589332.png",
      "description": "เสื้อ Sweater ผ้าหนานุ่ม เหมาะกับหน้าหนาว"
    },
    {
      "id": 16,
      "product_name": "เสื้อ Sweater สีดำ",
      "category": "Sweater",
      "color": "ดำ",
      "gender": "ชาย",
      "price": 530,
      "image": "https://png.pngtree.com/png-vector/20240708/ourmid/pngtree-black-sweater-mockup-png-image_13012907.png",
      "description": "เสื้อ Sweater สีดำคลาสสิค ใส่กับอะไรก็เท่"
    },
    {
      "id": 17,
      "product_name": "เสื้อ Sweater สีครีม",
      "category": "Sweater",
      "color": "ครีม",
      "gender": "หญิง",
      "price": 510,
      "image": "https://png.pngtree.com/png-vector/20250530/ourmid/pngtree-cream-turtleneck-sweater-front-view-isolated-on-white-png-image_16412263.png",
      "description": "เสื้อ Sweater สีครีมน่ารัก เหมาะกับอากาศเย็น"
    },
    {
      "id": 18,
      "product_name": "เสื้อ Sweater ลายหัวใจ",
      "category": "Sweater",
      "color": "ลายหัวใจ",
      "gender": "หญิง",
      "price": 520,
      "image": "https://png.pngtree.com/png-vector/20241211/ourmid/pngtree-cozy-pink-sweater-with-heart-motif-and-floral-embroidery-for-winter-png-image_14648847.png",
      "description": "Sweater ลายหัวใจ ผ้าอบอุ่น ใส่สบาย"
    },

    {
      "id": 19,
      "product_name": "เสื้อ Crop Top สีชมพู",
      "category": "Crop",
      "color": "ชมพู",
      "gender": "หญิง",
      "price": 290,
      "image": "https://img.th.my-best.com/product_images/b899a7108c8b8a180b6b12c4f2c81e35.png?ixlib=rails-4.3.1&q=70&lossless=0&w=800&h=800&fit=clip&s=2d84b57a937ea2ace109e8caf96ca7a7",
      "description": "Crop Top สีชมพูสดใส เหมาะกับวันสบายๆ"
    },
    {
      "id": 20,
      "product_name": "เสื้อ Crop Top สีดำ",
      "category": "Crop",
      "color": "ดำ",
      "gender": "หญิง",
      "price": 310,
      "image": "https://th.louisvuitton.com/images/is/image/lv/1/PP_VP_L/louis-vuitton-cropped-tshirt-w/-silk-ties--FTTS90ZHP900_PM1_Back%20view.jpg",
      "description": "Crop Top สีดำเท่ๆ ใส่กับกางเกงยีนส์ได้ทุกวัน"
    },
    {
      "id": 21,
      "product_name": "เสื้อ Crop Top แขนยาว",
      "category": "Crop",
      "color": "ขาว",
      "gender": "หญิง",
      "price": 320,
      "image": "https://png.pngtree.com/png-vector/20240721/ourmid/pngtree-sunnei-layered-long-sleeved-crop-top-png-image_13175668.png",
      "description": "Crop Top แขนยาว ผ้าคอตตอนนุ่ม"
    },

    {
      "id": 22,
      "product_name": "เสื้อ Polo ผู้ชาย ลายขวาง",
      "category": "Polo",
      "color": "ลายขวาง",
      "gender": "ชาย",
      "price": 470,
      "image": "https://png.pngtree.com/png-clipart/20240814/original/pngtree-boys-white-regular-fit-stripe-polo-neck-t-shirt-png-image_15772087.png",
      "description": "เสื้อโปโลผู้ชายลายขวาง สไตล์สปอร์ต"
    },
    {
      "id": 23,
      "product_name": "เสื้อ Oversize สีแดง",
      "category": "Oversize",
      "color": "แดง",
      "gender": "หญิง",
      "price": 365,
      "image": "https://png.pngtree.com/png-vector/20240124/ourmid/pngtree-red-isolated-t-shirt-png-image_11480334.png",
      "description": "เสื้อ Oversize สีแดงสดใส ใส่เที่ยวได้ทุกโอกาส"
    },
    {
      "id": 24,
      "product_name": "เสื้อ Oversize ผู้ชาย สีเบจ",
      "category": "Oversize",
      "color": "เบจ",
      "gender": "ชาย",
      "price": 390,
      "image": "https://png.pngtree.com/png-vector/20230922/ourmid/pngtree-tan-men-s-classic-t-shirt-front-and-back-png-image_10145665.png",
      "description": "เสื้อ Oversize ผู้ชาย สีเบจเข้ม ใส่เท่ๆ"
    },
    {
      "id": 25,
      "product_name": "เสื้อ Sweater ผู้ชาย สีกรม",
      "category": "Sweater",
      "color": "กรม",
      "gender": "ชาย",
      "price": 540,
      "image": "https://img.th.my-best.com/product_images/e3e1da4546bc6e5c3ca154fde70bba2f.png?ixlib=rails-4.3.1&q=70&lossless=0&w=800&h=800&fit=clip&s=1644220fa691f6b3e680b82b267804be",
      "description": "Sweater สีกรมเข้ม ดูสุภาพและเท่"
    },
    {
      "id": 26,
      "product_name": "เสื้อ Sweater ผู้หญิง สีฟ้าอ่อน",
      "category": "Sweater",
      "color": "ฟ้าอ่อน",
      "gender": "หญิง",
      "price": 500,
      "image": "https://inwfile.com/s-ds/b8z96z.jpg",
      "description": "Sweater สีฟ้าอ่อน ผ้านุ่มน่ารัก"
    },
    {
      "id": 27,
      "product_name": "เสื้อ Crop Top สีเหลือง",
      "category": "Crop",
      "color": "เหลือง",
      "gender": "หญิง",
      "price": 300,
      "image": "https://encrypted-tbn0.gstatic.com/images?q=tbn:ANd9GcS_kJmFrVea3bq2BUGM1E3vOT_pWrMv0zR8Rg&s",
      "description": "Crop Top สีเหลืองสดใส เพิ่มความมั่นใจ"
    },
    {
  "id": 28,
  "product_name": "กางเกงยีนส์ผู้ชาย สีเข้ม",
  "category": "Pants",
  "color": "น้ำเงินเข้ม",
  "gender": "ชาย",
  "price": 550,
  "image": "https://down-th.img.susercontent.com/file/cn-11134207-7ras8-m6gjknlsby4r09.webp",
  "description": "กางเกงยีนส์ทรงสลิมสีเข้ม ใส่ได้ทุกสไตล์"
},
{
  "id": 29,
  "product_name": "กางเกงยีนส์ผู้หญิง ขาเต่อ",
  "category": "Pants",
  "color": "น้ำเงินอ่อน",
  "gender": "หญิง",
  "price": 520,
  "image": "https://img.th.my-best.com/product_images/85c145273b36f03c62a474cee572e0ed.png?ixlib=rails-4.3.1&q=70&lossless=0&w=800&h=800&fit=clip&s=5a158eda7e79d3630c215c7cf9da589d",
  "description": "กางเกงยีนส์ขาเต่อผู้หญิง ใส่แล้วดูขายาว"
},
{
  "id": 30,
  "product_name": "เสื้อยืดเด็ก ลายหมี",
  "category": "Tshirt",
  "color": "น้ำตาล",
  "gender": "kids",
  "price": 250,
  "image": "https://png.pngtree.com/png-clipart/20240504/original/pngtree-teddy-bear-print-t-shirt-png-image_14815649.png",
  "description": "เสื้อยืดเด็กน่ารัก ลายหมีสำหรับทุกโอกาส"
},
{
  "id": 31,
  "product_name": "กางเกงขาสั้นเด็ก สีฟ้า",
  "category": "Pants",
  "color": "ฟ้า",
  "gender": "kids",
  "price": 230,
  "image": "https://png.pngtree.com/png-clipart/20230830/original/pngtree-kids-blue-shorts-png-image_13246660.png",
  "description": "กางเกงขาสั้นเด็กเบา ใส่สบายในทุกวัน"
},

{
  "id": 32,
  "product_name": "กางเกงยีนส์ผู้หญิง สีดำ",
  "category": "Pants",
  "color": "ดำ",
  "gender": "หญิง",
  "price": 540,
  "image": "https://cdn.shopify.com/s/files/1/0608/9726/3853/files/8859152612898__1_eab40df0-d810-44ba-b8d8-9863426bd3be_600x.jpg?v=1745564453",
  "description": "กางเกงยีนส์สีดำเข้ม ทรงสวย ใส่เข้ารูป"
},
{
  "id": 33,
  "product_name": "กางเกงขาสั้นผู้ชาย สีเบจ",
  "category": "Pants",
  "color": "เบจ",
  "gender": "ชาย",
  "price": 320,
  "image": "https://png.pngtree.com/png-vector/20230724/ourmid/pngtree-men-s-simple-khaki-shorts-png-image_7630277.png",
  "description": "กางเกงขาสั้นสีเบจ ใส่สบาย เหมาะกับวันชิลๆ"
},
{
  "id": 34,
  "product_name": "กางเกงยีนส์ผู้ชาย รุ่่น Classic Blue",
  "category": "Pants",
  "color": "น้ำเงิน",
  "gender": "ชาย",
  "price": 580,
  "image": "https://png.pngtree.com/png-vector/20230522/ourmid/pngtree-men-s-blue-jeans-png-image_7143331.png",
  "description": "ยีนส์สีน้ำเงินเข้ม ทรงตรง คลาสสิคตลอดกาล"
},
{
  "id": 35,
  "product_name": "กางเกงผ้าผู้หญิง ทรงกระบอก",
  "category": "Pants",
  "color": "ครีม",
  "gender": "หญิง",
  "price": 450,
  "image": "https://wrangler.co.th/cdn/shop/files/8859152985626__1_f7cb9b0d-401a-43fe-b261-77dff8594cf5_800x.jpg?v=1736872670",
  "description": "กางเกงผ้าทรงกระบอก ใส่สบาย ลุคมินิมอล"
},
{
  "id": 36,
  "product_name": "กางเกง Jogger ผู้ชาย สีเทา",
  "category": "Pants",
  "color": "เทา",
  "gender": "ชาย",
  "price": 390,
  "image": "https://png.pngtree.com/png-vector/20240226/ourmid/pngtree-mens-gray-jogger-pants-png-image_11678531.png",
  "description": "Jogger ผ้ายืด สปอร์ต ใส่ออกกำลังกายได้"
},
{
  "id": 37,
  "product_name": "เสื้อยืดเด็ก ลายไดโนเสาร์",
  "category": "Tshirt",
  "color": "ลายไดโนเสาร์",
  "gender": "kids",
  "price": 260,
  "image": "https://png.pngtree.com/png-vector/20230821/ourmid/pngtree-kids-dinosaur-graphic-t-shirt-png-image_13106127.png",
  "description": "เสื้อยืดเด็ก ลายไดโนเสาร์ สีสดใส"
},
{
  "id": 38,
  "product_name": "เสื้อยืดเด็ก ลายนางฟ้า",
  "category": "Tshirt",
  "color": "ลายนางฟ้า",
  "gender": "kids",
  "price": 270,
  "image": "https://png.pngtree.com/png-vector/20240607/ourmid/pngtree-cute-girl-kids-tshirt-graphic-design-png-image_12975392.png",
  "description": "เสื้อยืดเด็ก ลายการ์ตูนนางฟ้า น่ารักสดใส"
},
{
  "id": 39,
  "product_name": "กางเกงยีนส์เด็ก สีอ่อน",
  "category": "Pants",
  "color": "สีอ่อน",
  "gender": "kids",
  "price": 290,
  "image": "https://png.pngtree.com/png-vector/20240221/ourmid/pngtree-light-blue-kids-jeans-isolated-png-image_11643539.png",
  "description": "กางเกงยีนส์เด็กสีอ่อน ใส่ออกนอกบ้านได้ทุกวัน"
},
{
  "id": 40,
  "product_name": "เสื้อ Hoodies เด็ก สีชมพู",
  "category": "Sweater",
  "color": "ชมพู",
  "gender": "kids",
  "price": 350,
  "image": "https://png.pngtree.com/png-vector/20240206/ourmid/pngtree-pink-hoodie-front-view-kids-png-image_11598523.png",
  "description": "เสื้อฮู้ดเด็กผ้านิ่ม ใส่อบอุ่น"
},
{
  "id": 41,
  "product_name": "กางเกงวอร์มเด็ก สีกรม",
  "category": "Pants",
  "color": "กรม",
  "gender": "kids",
  "price": 280,
  "image": "https://png.pngtree.com/png-vector/20240206/ourmid/pngtree-kids-navy-jogger-pant--isolated-png-image_11598724.png",
  "description": "กางเกงวอร์มเด็ก ทรงลำลอง ใส่ได้ในทุกวัน"
},
{
  "id": 42,
  "product_name": "เสื้อยืดเด็ก ลายการ์ตูนไดโนเสาร์",
  "category": "Tshirt",
  "color": "ลายไดโนเสาร์",
  "gender": "kids",
  "price": 260,
  "image": "https://png.pngtree.com/png-vector/20230821/ourmid/pngtree-kids-dinosaur-graphic-t-shirt-png-image_13106127.png",
  "description": "เสื้อยืดเด็ก ลายไดโนเสาร์สีสดใส"
},
{
  "id": 43,
  "product_name": "เสื้อยืดเด็ก ลายยูนิคอร์น",
  "category": "Tshirt",
  "color": "ลายยูนิคอร์น",
  "gender": "kids",
  "price": 270,
  "image": "https://png.pngtree.com/png-vector/20240607/ourmid/pngtree-cute-girl-kids-tshirt-graphic-design-png-image_12975392.png",
  "description": "เสื้อยืดเด็ก น่ารักสไตล์ยูนิคอร์น"
},
{
  "id": 44,
  "product_name": "เสื้อยืดเด็ก สีเหลืองสด",
  "category": "Tshirt",
  "color": "เหลือง",
  "gender": "kids",
  "price": 240,
  "image": "https://png.pngtree.com/png-vector/20250523/ourlarge/pngtree-a-fashionable-woman-in-yellow-dress-and-stylish-accessories-png-image_16356787.png",
  "description": "เสื้อยืดเด็ก สีเหลืองสดใส ใส่แล้วดูเด่น"
},
{
  "id": 45,
  "product_name": "เสื้อยืดเด็ก สีชมพู น่ารัก",
  "category": "Tshirt",
  "color": "ชมพู",
  "gender": "kids",
  "price": 250,
  "image": "https://img.th.my-best.com/product_images/b899a7108c8b8a180b6b12c4f2c81e35.png?ixlib=rails-4.3.1&q=70&lossless=0&w=800&h=800&fit=clip&s=2d84b57a937ea2ace109e8caf96ca7a7",
  "description": "เสื้อยืดเด็กลุคหวาน นุ่มสบาย"
},
{
  "id": 46,
  "product_name": "เสื้อยืดเด็ก ลายหัวใจ",
  "category": "Tshirt",
  "color": "ลายหัวใจ",
  "gender": "kids",
  "price": 255,
  "image": "https://png.pngtree.com/png-vector/20241211/ourmid/pngtree-cozy-pink-sweater-with-heart-motif-and-floral-embroidery-for-winter-png-image_14648847.png",
  "description": "ลายน่ารัก ใส่แล้วดูสดใส"
},
{
  "id": 47,
  "product_name": "กางเกงยีนส์เด็ก สีอ่อน",
  "category": "Pants",
  "color": "สีอ่อน",
  "gender": "kids",
  "price": 290,
  "image": "https://png.pngtree.com/png-vector/20240221/ourmid/pngtree-light-blue-kids-jeans-isolated-png-image_11643539.png",
  "description": "ยีนส์เด็กโทนสว่าง ใส่เที่ยวได้"
},
{
  "id": 48,
  "product_name": "กางเกงขาสั้นเด็ก สีฟ้า",
  "category": "Pants",
  "color": "ฟ้า",
  "gender": "kids",
  "price": 230,
  "image": "https://png.pngtree.com/png-clipart/20230830/original/pngtree-kids-blue-shorts-png-image_13246660.png",
  "description": "ขาสั้นเด็ก ใส่สบายทุกวัน"
},
{
  "id": 49,
  "product_name": "กางเกงวอร์มเด็ก สีกรม",
  "category": "Pants",
  "color": "กรม",
  "gender": "kids",
  "price": 280,
  "image": "https://png.pngtree.com/png-vector/20240206/ourmid/pngtree-kids-navy-jogger-pant--isolated-png-image_11598724.png",
  "description": "กางเกงวอร์มเด็ก ใส่ออกกำลังกายได้"
},
{
  "id": 50,
  "product_name": "กางเกงผ้าเด็ก ทรงตรง",
  "category": "Pants",
  "color": "น้ำตาล",
  "gender": "kids",
  "price": 270,
  "image": "https://png.pngtree.com/png-vector/20240226/ourmid/pngtree-baby-boy-pants-isolated-png-image_11678577.png",
  "description": "ผ้าใส่สบาย เหมาะกับเด็กซน"
},
{
  "id": 51,
  "product_name": "กางเกงยีนส์เด็ก ขาดปลายเท่ๆ",
  "category": "Pants",
  "color": "น้ำเงิน",
  "gender": "kids",
  "price": 300,
  "image": "https://png.pngtree.com/png-vector/20240209/ourmid/pngtree-distressed-blue-jeans-kids-png-image_11605850.png",
  "description": "ยีนส์เด็กสไตล์แฟชั่น"
},
{
  "id": 52,
  "product_name": "เซ็ตเสื้อ-กางเกง ลายดอกไม้",
  "category": "Set",
  "color": "ลายดอกไม้",
  "gender": "kids",
  "price": 390,
  "image": "https://png.pngtree.com/png-vector/20240218/ourmid/pngtree-cute-baby-girls-dress-kids-png-image_11630397.png",
  "description": "ชุดเซ็ตน่ารัก ลายดอกสดใส"
},
{
  "id": 53,
  "product_name": "เซ็ตเสื้อโปโลเด็ก + กางเกงขาสั้น",
  "category": "Set",
  "color": "โปโลสีฟ้า",
  "gender": "kids",
  "price": 420,
  "image": "https://png.pngtree.com/png-vector/20240214/ourmid/pngtree-baby-poloshirt-and-shorts-set-png-image_11623549.png",
  "description": "ชุดเซ็ตเด็กคูลๆ ใส่ไปเที่ยว"
},
{
  "id": 54,
  "product_name": "เซ็ตเสื้อแขนยาว + กางเกงลายทาง",
  "category": "Set",
  "color": "ลายทาง",
  "gender": "kids",
  "price": 450,
  "image": "https://png.pngtree.com/png-vector/20240210/ourmid/pngtree-baby-boy-hoodie-pant-set-png-image_11607566.png",
  "description": "ชุดลำลอง ใส่สบาย"
},
{
  "id": 55,
  "product_name": "ชุดเด็กชาย สปอร์ตเซ็ต",
  "category": "Set",
  "color": "สปอร์ต",
  "gender": "kids",
  "price": 480,
  "image": "https://png.pngtree.com/png-vector/20240208/ourmid/pngtree-boys-sporty-tracksuit-kids-png-image_11601871.png",
  "description": "ลุคสปอร์ต เหมาะกับเล่นซน"
},
{
  "id": 56,
  "product_name": "เซ็ตเสื้อยืด + กางเกงยีนส์",
  "category": "Set",
  "color": "ยีนส์คลาสสิก",
  "gender": "kids",
  "price": 450,
  "image": "https://png.pngtree.com/png-vector/20240223/ourmid/pngtree-boy-outfit-set-children-png-image_11651463.png",
  "description": "ชุดเด็กเซ็ตคลาสสิก"
},
{
  "id": 57,
  "product_name": "Hoodie เด็ก สีชมพู",
  "category": "Sweater",
  "color": "ชมพู",
  "gender": "kids",
  "price": 350,
  "image": "https://png.pngtree.com/png-vector/20240206/ourmid/pngtree-pink-hoodie-front-view-kids-png-image_11598523.png",
  "description": "ฮู้ดเด็กผ้านิ่ม"
},
{
  "id": 58,
  "product_name": "Sweater เด็ก สีเทา",
  "category": "Sweater",
  "color": "เทา",
  "gender": "kids",
  "price": 340,
  "image": "https://png.pngtree.com/png-vector/20240202/ourmid/pngtree-gray-sweater-mockup-cutout-png-file-png-image_11589332.png",
  "description": "เสื้อกันหนาวเด็ก สีเทาเรียบ"
},
{
  "id": 59,
  "product_name": "Sweater เด็ก สีดำ",
  "category": "Sweater",
  "color": "ดำ",
  "gender": "kids",
  "price": 360,
  "image": "https://png.pngtree.com/png-vector/20240708/ourmid/pngtree-black-sweater-mockup-png-image_13012907.png",
  "description": "เสื้อกันหนาวเด็กคลาสสิค"
},
{
  "id": 60,
  "product_name": "Sweater เด็ก สีฟ้าอ่อน",
  "category": "Sweater",
  "color": "ฟ้าอ่อน",
  "gender": "kids",
  "price": 350,
  "image": "https://inwfile.com/s-ds/b8z96z.jpg",
  "description": "ผ้านุ่มใส่สบาย เหมาะกับอากาศเย็น"
},
{
  "id": 61,
  "product_name": "Hoodie เด็ก ลายหมี",
  "category": "Sweater",
  "color": "น้ำตาล",
  "gender": "kids",
  "price": 370,
  "image": "https://png.pngtree.com/png-vector/20240504/original/pngtree-teddy-bear-print-t-shirt-png-image_14815649.png",
  "description": "ฮู้ดเด็ก ลายหมีสุดน่ารัก"
},
{
  "id": 62,
  "product_name": "เดรสเด็ก ลายดอกไม้ สีชมพู",
  "category": "Dress",
  "color": "ชมพู",
  "gender": "kids",
  "price": 390,
  "image": "https://png.pngtree.com/png-vector/20240723/ourmid/pngtree-pink-floral-kids-dress-png-image_13136630.png",
  "description": "เดรสดอกไม้หวาน น่ารัก"
},
{
  "id": 63,
  "product_name": "เดรสเด็ก สีฟ้าพาสเทล",
  "category": "Dress",
  "color": "ฟ้าพาสเทล",
  "gender": "kids",
  "price": 420,
  "image": "https://png.pngtree.com/png-vector/20230508/ourmid/pngtree-baby-blue-dress-girls-png-image_909301.png",
  "description": "เดรสโทนฟ้า ลุคสดใสน่ารัก"
},
{
  "id": 64,
  "product_name": "เดรสเด็ก ลายริบบิ้น",
  "category": "Dress",
  "color": "ลายริบบิ้น",
  "gender": "kids",
  "price": 410,
  "image": "https://png.pngtree.com/png-vector/20241022/ourmid/pngtree-cute-kids-bow-dress-png-image_14329707.png",
  "description": "เดรสลายโบว์หวานมาก"
},
{
  "id": 65,
  "product_name": "เดรสเด็ก สีครีม นิ่มสบาย",
  "category": "Dress",
  "color": "ครีม",
  "gender": "kids",
  "price": 430,
  "image": "https://png.pngtree.com/png-vector/20250531/ourmid/pngtree-cute-cream-kids-dress-png-image_16416531.png",
  "description": "เดรสเด็กผ้านุ่ม ใส่สบาย"
},
{
  "id": 66,
  "product_name": "เดรสเด็ก ลายหัวใจแดง",
  "category": "Dress",
  "gender": "kids",
  "price": 440,
  "image": "https://png.pngtree.com/png-vector/20240721/ourmid/pngtree-sunnei-layered-long-sleeved-crop-top-png-image_13175668.png",
  "description": "ลายหัวใจเด่น สดใสน่ารัก"
}
  ],
  "customers": [
    {
      "id": 101,
      "first_name": "สมใจ",
      "last_name": "รักดี",
      "email": "somjai.r@example.com"
    },
    {
      "id": 102,
      "first_name": "วีระ",
      "last_name": "ใจกล้า",
      "email": "veera.j@example.com"
    },
    {
      "id": 103,
      "first_name": "อรุณี",
      "last_name": "สดใส",
      "email": "arunee.s@example.com"
    },
    {
      "id": 104,
      "first_name": "ดำรง",
      "last_name": "มั่นคง",
      "email": "damrong.m@example.com"
    },
    {
      "id": 105,
      "first_name": "แก้วตา",
      "last_name": "งดงาม",
      "email": "kaewta.n@example.com"
    }
  ],
  "reviews": [
    {
      "R_Id": 1,
      "User_Id": 101,
      "P_Id": 1,
      "rating": 5,
      "text": "เสื้อสวยมากค่ะ ผ้าดี นุ่มใส่สบาย ตรงปกเลย จัดส่งเร็วด้วย"
    },
    {
      "R_Id": 2,
      "User_Id": 102,
      "P_Id": 6,
      "rating": 4,
      "text": "สีเทาเข้มสวยดีครับ ทรงโอเวอร์ไซส์ตามที่ต้องการ แต่ผ้าอาจจะหนาไปนิดสำหรับหน้าร้อน"
    },
    {
      "R_Id": 3,
      "User_Id": 103,
      "P_Id": 13,
      "rating": 5,
      "text": "ถูกใจมากค่ะ โปโลสีชมพูอ่อนน่ารัก ใส่ไปทำงานได้สบายๆ ไม่ร้อน"
    },
    {
      "R_Id": 4,
      "User_Id": 104,
      "P_Id": 15,
      "rating": 3,
      "text": "Sweater อุ่นดีครับ แต่รู้สึกว่าแขนเสื้อยาวไปหน่อย"
    },
    {
      "R_Id": 5,
      "User_Id": 101,
      "P_Id": 20,
      "rating": 5,
      "text": "Crop Top สีดำตัวนี้แมทช์กับกางเกงยีนส์ได้ง่ายมาก เป็น Must Have เลยค่ะ"
    },
    {
      "R_Id": 6,
      "User_Id": 105,
      "P_Id": 27,
      "rating": 4,
      "text": "เสื้อ Sweater สีฟ้าอ่อนน่ารักดีค่ะ ผ้าไม่ได้หนามาก ใส่ในห้องแอร์กำลังดี"
    },
    {
      "R_Id": 7,
      "User_Id": 102,
      "P_Id": 10,
      "rating": 5,
      "text": "คุณภาพดีมากครับ โปโลสีกรมใส่แล้วดูดี ส่งไวมากครับ"
    },
    {
      "R_Id": 8,
      "User_Id": 103,
      "P_Id": 35,
      "rating": 4,
      "text": "สีม่วงลาเวนเดอร์สวยหวานมากค่ะ แต่ซักแล้วสีดูจางลงนิดนึง"
    },
    {
      "R_Id": 9,
      "User_Id": 104,
      "P_Id": 32,
      "rating": 5,
      "text": "โปโลสีแดงสดใส ผ้าไม่ย้วยเลยครับ คุ้มค่ามาก"
    },
    {
      "R_Id": 10,
      "User_Id": 105,
      "P_Id": 1,
      "rating": 4,
      "text": "ซื้อมาเป็นตัวที่สองแล้วค่ะ ชอบทรงมาก แต่รอบนี้มีด้ายหลุดนิดหน่อย"
    }
  ]
}